{
  "title": "수학 라이트 모의고사 Sample",
  "version": "v1",
  "totalQuestions": 18,
  "totalPoints": 58,
  "timeLimit": "60:00",
  "questions": [
    {
      "id": 1,
      "unit": "수학Ⅰ",
      "topic": "지수·로그",
      "type": "지수 계산",
      "diff": 1,
      "pts": 2,
      "rec": "1:00",
      "mode": "choice",
      "stem": "\\( 2^3 \\times 4^{-1} \\)의 값은?",
      "tex": "2^3 \\times 4^{-1}",
      "opts": ["① 1", "② 2", "③ 4", "④ 6", "⑤ 8"],
      "ans": 1,
      "solution": "4 = 2²이므로 4^{-1} = 2^{-2}이다. 따라서 2³ × 2^{-2} = 2^{3-2} = 2¹ = 2",
      "solTex": "2^3 \\times 4^{-1} = 2^3 \\times 2^{-2} = 2^1 = 2",
      "solNote": null
    },
    {
      "id": 2,
      "unit": "수학Ⅰ",
      "topic": "삼각함수",
      "type": "삼각방정식",
      "diff": 2,
      "pts": 3,
      "rec": "2:30",
      "mode": "choice",
      "stem": "0 ≤ θ < 2π일 때, 방정식 \\( 2\\sin^2\\theta - 3\\sin\\theta + 1 = 0 \\)의 모든 해의 합은?",
      "tex": "2\\sin^2\\theta - 3\\sin\\theta + 1 = 0",
      "opts": ["① π", "② \\dfrac{7\\pi}{6}", "③ \\dfrac{3\\pi}{2}", "④ \\dfrac{11\\pi}{6}", "⑤ 2π"],
      "ans": 2,
      "solution": "sin θ = t로 놓으면 2t² - 3t + 1 = 0, (2t-1)(t-1) = 0이므로 t = 1/2 또는 t = 1.\nsin θ = 1/2: θ = π/6, 5π/6. sin θ = 1: θ = π/2.\n모든 해의 합 = π/6 + 5π/6 + π/2 = π + π/2 = 3π/2",
      "solTex": "\\theta = \\frac{\\pi}{6},\\ \\frac{5\\pi}{6},\\ \\frac{\\pi}{2} \\quad \\Rightarrow \\quad \\text{합} = \\frac{3\\pi}{2}",
      "solNote": null
    },
    {
      "id": 3,
      "unit": "수학Ⅰ",
      "topic": "삼각함수",
      "type": "코사인법칙",
      "diff": 2,
      "pts": 3,
      "rec": "2:30",
      "mode": "choice",
      "stem": "삼각형 ABC에서 AB = 4, AC = 3, ∠A = 60°일 때, 변 BC의 길이는?",
      "tex": "AB = 4,\\ AC = 3,\\ \\angle A = 60°",
      "opts": ["① \\sqrt{7}", "② \\sqrt{13}", "③ \\sqrt{14}", "④ 4", "⑤ \\sqrt{19}"],
      "ans": 1,
      "solution": "코사인법칙: BC² = AB² + AC² - 2·AB·AC·cos A = 16 + 9 - 24·(1/2) = 25 - 12 = 13. BC = √13",
      "solTex": "BC^2 = 16 + 9 - 2(4)(3)\\cos 60° = 25 - 12 = 13 \\Rightarrow BC = \\sqrt{13}",
      "solNote": null
    },
    {
      "id": 4,
      "unit": "수학Ⅰ",
      "topic": "수열",
      "type": "등비수열의 합",
      "diff": 2,
      "pts": 3,
      "rec": "2:30",
      "mode": "short",
      "stem": "첫째항이 2이고 공비가 3인 등비수열 {a_n}에 대하여 \\( \\sum_{k=1}^{4} a_k \\)의 값을 구하시오.",
      "tex": "\\sum_{k=1}^{4} a_k",
      "opts": null,
      "ans": "80",
      "solution": "S₄ = 2·(3⁴ - 1)/(3 - 1) = 2·(81 - 1)/2 = 80. 또는 2 + 6 + 18 + 54 = 80",
      "solTex": "S_4 = \\frac{2(3^4-1)}{3-1} = \\frac{2 \\times 80}{2} = 80",
      "solNote": null
    },
    {
      "id": 5,
      "unit": "수학Ⅰ",
      "topic": "수열",
      "type": "시그마·일반항",
      "diff": 3,
      "pts": 4,
      "rec": "4:00",
      "mode": "choice",
      "stem": "수열 {a_n}이 모든 자연수 n에 대하여 \\( \\sum_{k=1}^{n} a_k = n^2 + 3n \\)을 만족시킬 때, \\( a_{10} \\)의 값은?",
      "tex": "\\sum_{k=1}^{n} a_k = n^2 + 3n",
      "opts": ["① 19", "② 21", "③ 22", "④ 23", "⑤ 25"],
      "ans": 2,
      "solution": "S_n = n² + 3n. n ≥ 2일 때 a_n = S_n - S_{n-1} = (n²+3n) - ((n-1)²+3(n-1)) = 2n + 2.\na₁ = S₁ = 4 = 2(1)+2 ✓. 따라서 a_{10} = 2(10)+2 = 22",
      "solTex": "a_n = S_n - S_{n-1} = 2n+2,\\quad a_{10} = 22",
      "solNote": null
    },
    {
      "id": 6,
      "unit": "수학Ⅰ",
      "topic": "수열",
      "type": "점화식",
      "diff": 4,
      "pts": 4,
      "rec": "7:00",
      "mode": "short",
      "stem": "수열 {a_n}이 a₁ = 1이고 모든 자연수 n에 대하여\n\\( a_{n+1} = \\begin{cases} a_n + 3 & (a_n < 10) \\\\ a_n - 7 & (a_n \\geq 10) \\end{cases} \\)\n을 만족시킬 때, \\( \\sum_{k=1}^{30} a_k \\)의 값을 구하시오.",
      "tex": "a_{n+1} = \\begin{cases} a_n + 3 & (a_n < 10) \\\\ a_n - 7 & (a_n \\geq 10) \\end{cases}",
      "opts": null,
      "ans": "215",
      "solution": "수열을 나열하면: 1, 4, 7, 10, 3, 6, 9, 12, 5, 8, 11, 4, 7, 10, 3, ...\na₂ = a₁₂ = 4이므로 n ≥ 2부터 주기 10으로 반복한다.\n한 주기(a₂~a₁₁) 합 = 4+7+10+3+6+9+12+5+8+11 = 75\nΣ(k=1~30) = a₁ + 주기2회(a₂~a₂₁) + 나머지9항(a₂₂~a₃₀)\n= 1 + 75×2 + (4+7+10+3+6+9+12+5+8)\n= 1 + 150 + 64 = 215",
      "solTex": "\\text{주기 10: 합 } 75,\\quad \\sum_{k=1}^{30} a_k = 1 + 150 + 64 = 215",
      "solNote": "a₂부터 주기 10 반복을 찾는 것이 핵심"
    },
    {
      "id": 7,
      "unit": "수학Ⅱ",
      "topic": "극한",
      "type": "함수의 극한",
      "diff": 1,
      "pts": 2,
      "rec": "1:00",
      "mode": "choice",
      "stem": "\\( \\lim_{x \\to 1} \\dfrac{x^2 - 1}{x - 1} \\)의 값은?",
      "tex": "\\lim_{x \\to 1} \\frac{x^2-1}{x-1}",
      "opts": ["① 0", "② 1", "③ 2", "④ 3", "⑤ 4"],
      "ans": 2,
      "solution": "(x²-1)/(x-1) = (x+1)(x-1)/(x-1) = x+1. x→1이면 x+1→2",
      "solTex": "\\lim_{x \\to 1} \\frac{(x+1)(x-1)}{x-1} = \\lim_{x \\to 1}(x+1) = 2",
      "solNote": null
    },
    {
      "id": 8,
      "unit": "수학Ⅱ",
      "topic": "극한·연속",
      "type": "연속 조건",
      "diff": 2,
      "pts": 3,
      "rec": "2:30",
      "mode": "choice",
      "stem": "함수 \\( f(x) = \\begin{cases} \\dfrac{x^2 - 4}{x - 2} & (x \\neq 2) \\\\\\\\ a & (x = 2) \\end{cases} \\)가 x = 2에서 연속일 때, 상수 a의 값은?",
      "tex": "f(x) = \\begin{cases} \\dfrac{x^2-4}{x-2} & (x \\neq 2) \\\\ a & (x=2) \\end{cases}",
      "opts": ["① 0", "② 2", "③ 4", "④ 6", "⑤ 8"],
      "ans": 2,
      "solution": "x ≠ 2일 때 f(x) = (x+2)(x-2)/(x-2) = x+2. lim(x→2) f(x) = 4. 연속이려면 a = 4",
      "solTex": "\\lim_{x \\to 2} \\frac{(x+2)(x-2)}{x-2} = 4 \\Rightarrow a = 4",
      "solNote": null
    },
    {
      "id": 9,
      "unit": "수학Ⅱ",
      "topic": "미분",
      "type": "접선의 방정식",
      "diff": 2,
      "pts": 3,
      "rec": "2:30",
      "mode": "choice",
      "stem": "곡선 \\( y = x^3 - 3x \\) 위의 점 (1, -2)에서의 접선의 기울기는?",
      "tex": "y = x^3 - 3x",
      "opts": ["① -3", "② -1", "③ 0", "④ 1", "⑤ 3"],
      "ans": 2,
      "solution": "y' = 3x² - 3. x = 1에서 y' = 3 - 3 = 0. 확인: y(1) = 1 - 3 = -2 ✓",
      "solTex": "y' = 3x^2 - 3,\\quad y'(1) = 0",
      "solNote": null
    },
    {
      "id": 10,
      "unit": "수학Ⅱ",
      "topic": "미분",
      "type": "증감·극값",
      "diff": 2,
      "pts": 3,
      "rec": "3:00",
      "mode": "short",
      "stem": "함수 \\( f(x) = x^3 - 6x^2 + 9x + 2 \\)의 극댓값과 극솟값의 합을 구하시오.",
      "tex": "f(x) = x^3 - 6x^2 + 9x + 2",
      "opts": null,
      "ans": "8",
      "solution": "f'(x) = 3x²-12x+9 = 3(x-1)(x-3). 극대: f(1) = 1-6+9+2 = 6. 극소: f(3) = 27-54+27+2 = 2. 합 = 8",
      "solTex": "f'(x) = 3(x-1)(x-3),\\quad f(1)=6,\\ f(3)=2,\\quad 6+2=8",
      "solNote": null
    },
    {
      "id": 11,
      "unit": "수학Ⅱ",
      "topic": "미분",
      "type": "함수 결정",
      "diff": 3,
      "pts": 4,
      "rec": "4:30",
      "mode": "choice",
      "stem": "최고차항의 계수가 1인 삼차함수 f(x)가 다음 조건을 만족시킨다.\n(가) f'(1) = 0\n(나) f'(3) = 0\n(다) f(0) = 5\nf(4)의 값은?",
      "tex": "f'(1)=0,\\quad f'(3)=0,\\quad f(0)=5",
      "opts": ["① 5", "② 7", "③ 9", "④ 11", "⑤ 13"],
      "ans": 2,
      "solution": "f(x) = x³+bx²+cx+d. f'(x) = 3x²+2bx+c.\nf'(1)=0: 3+2b+c=0. f'(3)=0: 27+6b+c=0.\n뺄셈: 24+4b=0 → b=-6. c=9. f(0)=d=5.\nf(x) = x³-6x²+9x+5. f(4) = 64-96+36+5 = 9",
      "solTex": "f(x) = x^3-6x^2+9x+5,\\quad f(4) = 64-96+36+5 = 9",
      "solNote": null
    },
    {
      "id": 12,
      "unit": "수학Ⅱ",
      "topic": "적분",
      "type": "정적분 계산",
      "diff": 2,
      "pts": 3,
      "rec": "2:30",
      "mode": "choice",
      "stem": "\\( \\int_0^2 (3x^2 + 2x) \\, dx \\)의 값은?",
      "tex": "\\int_0^2 (3x^2+2x)\\,dx",
      "opts": ["① 8", "② 10", "③ 12", "④ 14", "⑤ 16"],
      "ans": 2,
      "solution": "∫(3x²+2x)dx = x³+x²+C. [x³+x²]₀² = (8+4) - 0 = 12",
      "solTex": "\\left[x^3+x^2\\right]_0^2 = 8+4 = 12",
      "solNote": null
    },
    {
      "id": 13,
      "unit": "수학Ⅱ",
      "topic": "적분",
      "type": "정적분과 미분 관계",
      "diff": 4,
      "pts": 4,
      "rec": "7:00",
      "mode": "short",
      "stem": "다항함수 f(x)가 모든 실수 x에 대하여\n\\( \\int_0^x f(t) \\, dt = x \\cdot f(x) - 2x^3 \\)\n을 만족시키고 f(1) = -17일 때, f(3)의 값을 구하시오.",
      "tex": "\\int_0^x f(t)\\,dt = x \\cdot f(x) - 2x^3,\\quad f(1) = -17",
      "opts": null,
      "ans": "7",
      "solution": "양변을 x에 대해 미분하면 f(x) = f(x) + xf'(x) - 6x².\n정리하면 xf'(x) = 6x², 즉 f'(x) = 6x (x ≠ 0).\n연속성에 의해 f'(0) = 0도 성립. f(x) = 3x² + C.\nf(1) = 3 + C = -17 → C = -20.\nf(x) = 3x² - 20. f(3) = 27 - 20 = 7.\n검산: ∫₀ˣ(3t²-20)dt = x³-20x. x·f(x)-2x³ = x(3x²-20)-2x³ = x³-20x ✓",
      "solTex": "xf'(x)=6x^2 \\Rightarrow f'(x)=6x \\Rightarrow f(x)=3x^2+C\\\\ f(1)=-17: C=-20\\\\ f(3)=27-20=7",
      "solNote": "양변을 미분하고, 조건으로 상수 결정"
    },
    {
      "id": 14,
      "unit": "확률과통계",
      "topic": "경우의 수",
      "type": "조합",
      "diff": 2,
      "pts": 3,
      "rec": "2:30",
      "mode": "choice",
      "stem": "서로 다른 5개의 공 중에서 3개를 선택하는 경우의 수와, 서로 다른 4개의 공 중에서 2개를 선택하는 경우의 수의 합은?",
      "tex": "\\binom{5}{3} + \\binom{4}{2}",
      "opts": ["① 14", "② 16", "③ 18", "④ 20", "⑤ 22"],
      "ans": 1,
      "solution": "C(5,3) = 10, C(4,2) = 6. 합 = 16",
      "solTex": "\\binom{5}{3}+\\binom{4}{2} = 10+6 = 16",
      "solNote": null
    },
    {
      "id": 15,
      "unit": "확률과통계",
      "topic": "확률",
      "type": "조건부확률",
      "diff": 2,
      "pts": 3,
      "rec": "3:00",
      "mode": "choice",
      "stem": "주머니에 흰 공 3개, 검은 공 2개가 들어 있다. 공을 하나 꺼내어 색을 확인한 후 되돌려 놓지 않고 다시 하나를 꺼낼 때, 첫 번째 공이 검은 공이었을 때 두 번째 공이 흰 공일 확률은?",
      "tex": "P(\\text{2nd white} \\mid \\text{1st black})",
      "opts": ["① \\dfrac{1}{4}", "② \\dfrac{1}{3}", "③ \\dfrac{1}{2}", "④ \\dfrac{3}{4}", "⑤ \\dfrac{3}{5}"],
      "ans": 3,
      "solution": "첫 번째에 검은 공을 꺼낸 후 남은 공: 흰 3개, 검은 1개 (총 4개). 흰 공을 꺼낼 확률 = 3/4",
      "solTex": "P = \\frac{3}{4}",
      "solNote": null
    },
    {
      "id": 16,
      "unit": "확률과통계",
      "topic": "통계",
      "type": "정규분포",
      "diff": 2,
      "pts": 3,
      "rec": "3:00",
      "mode": "choice",
      "stem": "확률변수 X가 정규분포 N(50, 5²)을 따를 때, P(45 ≤ X ≤ 60)의 값은?\n(단, P(0 ≤ Z ≤ 1) = 0.3413, P(0 ≤ Z ≤ 2) = 0.4772)",
      "tex": "X \\sim N(50,\\ 5^2)",
      "opts": ["① 0.3413", "② 0.4772", "③ 0.6826", "④ 0.8185", "⑤ 0.9544"],
      "ans": 3,
      "solution": "Z = (X-50)/5로 표준화.\nP(45≤X≤60) = P(-1≤Z≤2) = P(-1≤Z≤0) + P(0≤Z≤2) = 0.3413 + 0.4772 = 0.8185",
      "solTex": "P(-1 \\le Z \\le 2) = 0.3413 + 0.4772 = 0.8185",
      "solNote": null
    },
    {
      "id": 17,
      "unit": "확률과통계",
      "topic": "확률",
      "type": "독립시행",
      "diff": 3,
      "pts": 4,
      "rec": "4:30",
      "mode": "choice",
      "stem": "한 개의 동전을 6번 던질 때, 앞면이 4번 이상 나올 확률은?",
      "tex": "P(X \\geq 4),\\quad X \\sim B\\!\\left(6,\\frac{1}{2}\\right)",
      "opts": ["① \\dfrac{11}{64}", "② \\dfrac{15}{64}", "③ \\dfrac{11}{32}", "④ \\dfrac{5}{16}", "⑤ \\dfrac{1}{4}"],
      "ans": 2,
      "solution": "P(X=4) = C(6,4)·(1/2)⁶ = 15/64. P(X=5) = C(6,5)·(1/2)⁶ = 6/64. P(X=6) = C(6,6)·(1/2)⁶ = 1/64.\nP(X≥4) = (15+6+1)/64 = 22/64 = 11/32",
      "solTex": "P(X \\ge 4) = \\frac{15+6+1}{64} = \\frac{22}{64} = \\frac{11}{32}",
      "solNote": null
    },
    {
      "id": 18,
      "unit": "확률과통계",
      "topic": "확률·통계",
      "type": "조건부확률 종합",
      "diff": 4,
      "pts": 4,
      "rec": "7:00",
      "mode": "short",
      "stem": "공장 A, B에서 전체 제품의 40%, 60%를 각각 생산한다. A 공장 제품의 불량률은 5%, B 공장 제품의 불량률은 10%이다. 임의로 선택한 제품이 불량품일 때, 이것이 B 공장 제품일 확률을 p라 하자. 100p의 값을 구하시오.",
      "tex": "P(B \\mid D) = p",
      "opts": null,
      "ans": "75",
      "solution": "P(A)=0.4, P(B)=0.6, P(D|A)=0.05, P(D|B)=0.10.\nP(D) = 0.05×0.4 + 0.10×0.6 = 0.02 + 0.06 = 0.08.\nP(B|D) = P(D|B)P(B)/P(D) = 0.06/0.08 = 3/4.\n100p = 75",
      "solTex": "P(B|D) = \\frac{0.06}{0.08} = \\frac{3}{4},\\quad 100p = 75",
      "solNote": "베이즈 정리 적용. 전확률 공식으로 P(D)를 먼저 구한다."
    }
  ]
}
